binsmith/__init__.py
binsmith/__main__.py
binsmith/cli.py
binsmith/env.py
binsmith/linker.py
binsmith/plugin.py
binsmith/tools.py
binsmith/workspace.py
binsmith-0.5.2.dist-info/METADATA
binsmith-0.5.2.dist-info/WHEEL
binsmith-0.5.2.dist-info/entry_points.txt
binsmith-0.5.2.dist-info/RECORD
