Metadata-Version: 2.4
Name: binsmith
Version: 0.5.2
Summary: Binsmith agent plugin for Lattis
Project-URL: Homepage, https://github.com/caesarnine/binsmith
Project-URL: Repository, https://github.com/caesarnine/binsmith
Project-URL: Issues, https://github.com/caesarnine/binsmith/issues
License-Expression: MIT
Keywords: agent,ai,automation,cli,tools
Classifier: Development Status :: 3 - Alpha
Classifier: Environment :: Console
Classifier: Intended Audience :: Developers
Classifier: License :: OSI Approved :: MIT License
Classifier: Programming Language :: Python :: 3.12
Classifier: Topic :: Software Development :: Libraries :: Application Frameworks
Requires-Python: >=3.12
Requires-Dist: lattis>=0.5.0
Requires-Dist: logfire>=3.0.0
